LICENSE
README.md
setup.py
stitches/__init__.py
stitches/connection.py
stitches/expect.py
stitches/structure.py
stitches.egg-info/PKG-INFO
stitches.egg-info/SOURCES.txt
stitches.egg-info/dependency_links.txt
stitches.egg-info/requires.txt
stitches.egg-info/top_level.txt