Metadata-Version: 2.1
Name: stitches
Version: 0.19
Summary: Multihost actions toolbox
Home-page: https://github.com/RedHatQE/python-stitches
Author: Vitaly Kuznetsov
Author-email: vitty@redhat.com
License: GPLv3+
Classifier: License :: OSI Approved :: GNU General Public License v3 or later (GPLv3+)
Classifier: Programming Language :: Python
Classifier: Topic :: Software Development :: Libraries :: Python Modules
Classifier: Operating System :: POSIX
Classifier: Intended Audience :: Developers
Classifier: Development Status :: 4 - Beta
License-File: LICENSE
Requires-Dist: paramiko>=1.10
Requires-Dist: nose
Requires-Dist: PyYAML
Requires-Dist: plumbum
Requires-Dist: rpyc
